russian_coast/__init__.py
russian_coast/russian_cost.py
russian_coast/test.py
russian_cost-0.0.2.dist-info/METADATA
russian_cost-0.0.2.dist-info/WHEEL
russian_cost-0.0.2.dist-info/top_level.txt
russian_cost-0.0.2.dist-info/RECORD
