Metadata-Version: 2.1
Name: russian-cost
Version: 0.0.2
Summary: Module for converting russian cost to string
Home-page: https://github.com/zzzkorn/russian_cost
Author: zzzkorn
Author-email: pavelevseev92@yandex.ru
License: BSD (3 clause)
Project-URL: Bug Tracker, https://github.com/zzzkorn/russian_cost/issues
Platform: UNKNOWN
Classifier: License :: OSI Approved :: BSD License
Classifier: Programming Language :: Python :: 3
Classifier: Programming Language :: Python :: 3 :: Only
Classifier: Programming Language :: Python :: Implementation :: CPython
Classifier: Programming Language :: Python :: Implementation :: PyPy
Classifier: Topic :: Text Processing
Requires-Python: >=3.1
Provides-Extra: tests
Requires-Dist: pytest ; extra == 'tests'
